fastapi_block_hunter/__init__.py
fastapi_block_hunter/src.py
fastapi_block_hunter-0.0.1.dist-info/LICENSE
fastapi_block_hunter-0.0.1.dist-info/METADATA
fastapi_block_hunter-0.0.1.dist-info/WHEEL
fastapi_block_hunter-0.0.1.dist-info/RECORD
