Metadata-Version: 2.3
Name: fastapi-block-hunter
Version: 0.0.1
Summary: A FastAPI-based block hunter application
Home-page: https://github.com/yourusername/fastapi-block-hunter
License: MIT
Keywords: fastapi,block-hunter
Author: Manuel Angel Suarez Alvarez
Author-email: Manuel_Angel99@outlook.com
Requires-Python: >=3.11,<4.0
Classifier: Development Status :: 3 - Alpha
Classifier: Framework :: FastAPI
Classifier: License :: OSI Approved :: MIT License
Classifier: Programming Language :: Python :: 3
Classifier: Programming Language :: Python :: 3.11
Classifier: Programming Language :: Python :: 3.12
Classifier: Programming Language :: Python :: 3.13
Requires-Dist: fastapi (==0.103.2)
Project-URL: Repository, https://github.com/yourusername/fastapi-block-hunter
